what/__init__.py
what/__main__.py
what/_main.py
what/attacks/__init__.py
what/attacks/detection/__init__.py
what/attacks/detection/yolo/PCB.py
what/attacks/detection/yolo/TOG.py
what/attacks/detection/yolo/__init__.py
what/cli/__init__.py
what/cli/attack.py
what/cli/example.py
what/cli/model.py
what/examples/__init__.py
what/examples/faster_rcnn_demo.py
what/examples/mobilenet_ssd_demo.py
what/examples/yolov3_demo.py
what/examples/yolov3_pcb_attack_demo.py
what/examples/yolov3_tog_attack_demo.py
what/examples/yolov4_demo.py
what/examples/yolox_demo.py
what/models/__init__.py
what/models/detection/__init__.py
what/models/detection/datasets/__init__.py
what/models/detection/datasets/coco.py
what/models/detection/datasets/fiftyone.py
what/models/detection/datasets/open_images.py
what/models/detection/datasets/voc.py
what/models/detection/frcnn/__init__.py
what/models/detection/frcnn/faster_rcnn.py
what/models/detection/frcnn/datasets/__init__.py
what/models/detection/frcnn/datasets/dataset.py
what/models/detection/frcnn/datasets/util.py
what/models/detection/frcnn/datasets/voc_dataset.py
what/models/detection/frcnn/meter/__init__.py
what/models/detection/frcnn/meter/averagevalue_meter.py
what/models/detection/frcnn/meter/confusion_meter.py
what/models/detection/frcnn/meter/meter.py
what/models/detection/frcnn/model/__init__.py
what/models/detection/frcnn/model/faster_rcnn_model.py
what/models/detection/frcnn/model/faster_rcnn_vgg16.py
what/models/detection/frcnn/model/region_proposal_network.py
what/models/detection/frcnn/model/utils/__init__.py
what/models/detection/frcnn/model/utils/bbox_tools.py
what/models/detection/frcnn/model/utils/creator_tool.py
what/models/detection/frcnn/utils/__init__.py
what/models/detection/frcnn/utils/config.py
what/models/detection/frcnn/utils/eval_tool.py
what/models/detection/ssd/__init__.py
what/models/detection/ssd/mobilenet_v1_ssd.py
what/models/detection/ssd/mobilenet_v2_ssd_lite.py
what/models/detection/ssd/nn/__init__.py
whitebox_adversarial_toolbox-0.2.3.dist-info/LICENSE
whitebox_adversarial_toolbox-0.2.3.dist-info/METADATA
whitebox_adversarial_toolbox-0.2.3.dist-info/WHEEL
whitebox_adversarial_toolbox-0.2.3.dist-info/entry_points.txt
whitebox_adversarial_toolbox-0.2.3.dist-info/top_level.txt
whitebox_adversarial_toolbox-0.2.3.dist-info/RECORD
