Metadata-Version: 2.1
Name: whitebox-adversarial-toolbox
Version: 0.2.3
Summary: WHite-box Adversarial Toolbox (WHAT) - Python Library for Deep Learning Security
Home-page: https://github.com/wuhanstudio/whitebox-adversarial-toolbox
Author: wuhanstudio
Author-email: wuhanstudio <wuhanstudios@gmail.com>
Maintainer: wuhanstudio
Maintainer-email: wuhanstudio <wuhanstudios@gmail.com>
License: MIT License
Project-URL: Homepage, https://github.com/wuhanstudio/whitebox-adversarial-toolbox
Project-URL: Bug Tracker, https://github.com/wuhanstudio/whitebox-adversarial-toolbox/issues
Classifier: Intended Audience :: Science/Research
Classifier: License :: OSI Approved :: MIT License
Classifier: Programming Language :: Python :: 3.6
Classifier: Programming Language :: Python :: 3.7
Classifier: Programming Language :: Python :: 3.8
Classifier: Programming Language :: Python :: 3.9
Classifier: Topic :: Scientific/Engineering :: Artificial Intelligence
Requires-Python: >=3.6
License-File: LICENSE
Requires-Dist: numpy >=1.18.0
Requires-Dist: tqdm
Requires-Dist: six
Requires-Dist: setuptools
Requires-Dist: torch ==1.11.0
Requires-Dist: torchvision
Requires-Dist: opencv-python
Requires-Dist: scikit-image
Requires-Dist: tensorflow ==2.4.0
Requires-Dist: keras ==2.4.3
Requires-Dist: h5py ==2.10.0
Requires-Dist: matplotlib
Requires-Dist: pandas
Requires-Dist: click
Requires-Dist: progressbar
